{
    "Chennai": {
      "Soil Type": "Alluvial"
    },
    "Coimbatore": {
      "Soil Type": "Black"
    },
    "Madurai": {
      "Soil Type": "Black"
    },
    "Tiruchirappalli": {
      "Soil Type": "Alluvial"
    },
    "Salem": {
      "Soil Type": "Red"
    },
    "Tirunelveli": {
      "Soil Type": "Black"
    },
    "Erode": {
      "Soil Type": "Red"
    },
    "Vellore": {
      "Soil Type": "Red"
    },
    "Thoothukudi": {
      "Soil Type": "Coastal"
    },
    "Tiruppur": {
      "Soil Type": "Red"
    },
    "Kanniyakumari": {
      "Soil Type": "Coastal"
    },
    "Thanjavur": {
      "Soil Type": "Alluvial"
    },
    "Namakkal": {
      "Soil Type": "Red"
    },
    "Chengalpattu": {
      "Soil Type": "Alluvial"
    },
    "Nagapattinam": {
      "Soil Type": "Coastal"
    },
    "Dindigul": {
      "Soil Type": "Black"
    },
    "Ramanathapuram": {
      "Soil Type": "Red"
    },
    "Krishnagiri": {
      "Soil Type": "Red"
    },
    "Cuddalore": {
      "Soil Type": "Coastal"
    },
    "Villupuram": {
      "Soil Type": "Red"
    },
    "Tiruvannamalai": {
      "Soil Type": "Red"
    },
    "Tirupathur": {
      "Soil Type": "Red"
    },
    "Sivaganga": {
      "Soil Type": "Red"
    },
    "Perambalur": {
      "Soil Type": "Red"
    },
    "Ariyalur": {
      "Soil Type": "Red"
    },
    "Karur": {
      "Soil Type": "Red"
    },
    "Nilgiris": {
      "Soil Type": "Laterite"
    },
    "Ooty": {
      "Soil Type": "Laterite"
    },
    "Dharmapuri": {
      "Soil Type": "Red"
    },
    "Tiruvarur": {
      "Soil Type": "Alluvial"
    },
    "Virudhunagar": {
      "Soil Type": "Black"
    },
    "Tenkasi": {
      "Soil Type": "Black"
    },
    "Ranipet": {
      "Soil Type": "Red"
    },
    "Tiruvallur": {
      "Soil Type": "Alluvial"
    },
    "Kallakurichi": {
      "Soil Type": "Red"
    },
    "Tirupattur": {
      "Soil Type": "Red"
    },
    "Thirumangalam": {
      "Soil Type": "Black"
    },
    "Usilampatti": {
      "Soil Type": "Black"
    },
    "Lalgudi": {
      "Soil Type": "Red"
    },
    "Thuraiyur": {
      "Soil Type": "Red"
    },
    "Mettur": {
      "Soil Type": "Red"
    },
    "Attur": {
      "Soil Type": "Red"
    },
    "Omalur": {
      "Soil Type": "Red"
    },
    "Palayamkottai": {
      "Soil Type": "Black"
    },
    "Nanguneri": {
      "Soil Type": "Black"
    },
    "Bhavani": {
      "Soil Type": "Red"
    },
    "Gobichettipalayam": {
      "Soil Type": "Red"
    },
    "Arakkonam": {
      "Soil Type": "Red"
    },
    "Gudiyatham": {
      "Soil Type": "Red"
    },
    "Kovilpatti": {
      "Soil Type": "Black"
    }
  }
  