{
    "Arakkonam": {
        "Soil Type": "Red"
    },
    "Ariyalur": {
        "Soil Type": "Red"
    },
    "Attur": {
        "Soil Type": "Red"
    },
    "Bhavani": {
        "Soil Type": "Red"
    },
    "Chengalpattu": {
        "Soil Type": "Alluvial"
    },
    "Chennai": {
        "Soil Type": "Alluvial"
    },
    "Coimbatore": {
        "Soil Type": "Black"
    },
    "Cuddalore": {
        "Soil Type": "Coastal"
    },
    "Dharmapuri": {
        "Soil Type": "Red"
    },
    "Dindigul": {
        "Soil Type": "Black"
    },
    "Erode": {
        "Soil Type": "Red"
    },
    "Gobichettipalayam": {
        "Soil Type": "Red"
    },
    "Gudiyatham": {
        "Soil Type": "Red"
    },
    "Kallakurichi": {
        "Soil Type": "Red"
    },
    "Kanniyakumari": {
        "Soil Type": "Coastal"
    },
    "Karur": {
        "Soil Type": "Red"
    },
    "Kovilpatti": {
        "Soil Type": "Black"
    },
    "Krishnagiri": {
        "Soil Type": "Red"
    },
    "Lalgudi": {
        "Soil Type": "Red"
    },
    "Madurai": {
        "Soil Type": "Black"
    },
    "Mettur": {
        "Soil Type": "Red"
    },
    "Nagapattinam": {
        "Soil Type": "Coastal"
    },
    "Namakkal": {
        "Soil Type": "Red"
    },
    "Nanguneri": {
        "Soil Type": "Black"
    },
    "Nilgiris": {
        "Soil Type": "Laterite"
    },
    "Omalur": {
        "Soil Type": "Red"
    },
    "Ooty": {
        "Soil Type": "Laterite"
    },
    "Palayamkottai": {
        "Soil Type": "Black"
    },
    "Perambalur": {
        "Soil Type": "Red"
    },
    "Ramanathapuram": {
        "Soil Type": "Red"
    },
    "Ranipet": {
        "Soil Type": "Red"
    },
    "Salem": {
        "Soil Type": "Red"
    },
    "Sivaganga": {
        "Soil Type": "Red"
    },
    "Tenkasi": {
        "Soil Type": "Black"
    },
    "Thanjavur": {
        "Soil Type": "Alluvial"
    },
    "Thirumangalam": {
        "Soil Type": "Black"
    },
    "Thoothukudi": {
        "Soil Type": "Coastal"
    },
    "Thuraiyur": {
        "Soil Type": "Red"
    },
    "Tiruchirappalli": {
        "Soil Type": "Alluvial"
    },
    "Tirunelveli": {
        "Soil Type": "Black"
    },
    "Tirupathur": {
        "Soil Type": "Red"
    },
    "Tirupattur": {
        "Soil Type": "Red"
    },
    "Tiruppur": {
        "Soil Type": "Red"
    },
    "Tiruvallur": {
        "Soil Type": "Alluvial"
    },
    "Tiruvannamalai": {
        "Soil Type": "Red"
    },
    "Tiruvarur": {
        "Soil Type": "Alluvial"
    },
    "Usilampatti": {
        "Soil Type": "Black"
    },
    "Vellore": {
        "Soil Type": "Red"
    },
    "Villupuram": {
        "Soil Type": "Red"
    },
    "Virudhunagar": {
        "Soil Type": "Black"
    }
}